chartjs/__init__.py
chartjs/colors.py
chartjs/models.py
chartjs/util.py
chartjs/static/css/Chart.min.css
chartjs/static/js/Chart.min.js
chartjs/static/js/excanvas.js
chartjs/static/js/highcharts/highcharts-more.js
chartjs/static/js/highcharts/highcharts-more.src.js
chartjs/static/js/highcharts/highcharts.js
chartjs/static/js/highcharts/highcharts.src.js
chartjs/static/js/highcharts/.fr-amL3gv/annotations.js
chartjs/static/js/highcharts/.fr-amL3gv/annotations.src.js
chartjs/static/js/highcharts/.fr-amL3gv/canvas-tools.js
chartjs/static/js/highcharts/.fr-amL3gv/canvas-tools.src.js
chartjs/static/js/highcharts/.fr-amL3gv/dark-blue.js
chartjs/static/js/highcharts/.fr-amL3gv/dark-green.js
chartjs/static/js/highcharts/.fr-amL3gv/data.js
chartjs/static/js/highcharts/.fr-amL3gv/data.src.js
chartjs/static/js/highcharts/.fr-amL3gv/exporting.js
chartjs/static/js/highcharts/.fr-amL3gv/exporting.src.js
chartjs/static/js/highcharts/.fr-amL3gv/funnel.js
chartjs/static/js/highcharts/.fr-amL3gv/funnel.src.js
chartjs/static/js/highcharts/.fr-amL3gv/gray.js
chartjs/static/js/highcharts/.fr-amL3gv/grid.js
chartjs/static/js/highcharts/.fr-amL3gv/highcharts-more.js
chartjs/static/js/highcharts/.fr-amL3gv/highcharts-more.src.js
chartjs/static/js/highcharts/.fr-amL3gv/highcharts.js
chartjs/static/js/highcharts/.fr-amL3gv/highcharts.src.js
chartjs/static/js/highcharts/.fr-amL3gv/skies.js
chartjs/static/js/highcharts/modules/annotations.js
chartjs/static/js/highcharts/modules/annotations.src.js
chartjs/static/js/highcharts/modules/canvas-tools.js
chartjs/static/js/highcharts/modules/canvas-tools.src.js
chartjs/static/js/highcharts/modules/data.js
chartjs/static/js/highcharts/modules/data.src.js
chartjs/static/js/highcharts/modules/exporting.js
chartjs/static/js/highcharts/modules/exporting.src.js
chartjs/static/js/highcharts/modules/funnel.js
chartjs/static/js/highcharts/modules/funnel.src.js
chartjs/static/js/highcharts/themes/dark-blue.js
chartjs/static/js/highcharts/themes/dark-green.js
django_chartjs-2.3.0.dist-info/AUTHORS
django_chartjs-2.3.0.dist-info/LICENSE
django_chartjs-2.3.0.dist-info/METADATA
django_chartjs-2.3.0.dist-info/WHEEL
django_chartjs-2.3.0.dist-info/top_level.txt
django_chartjs-2.3.0.dist-info/RECORD
