Metadata-Version: 1.1
Name: django-chartjs
Version: 2.3.0
Summary: Django Chart.js and Hightchart ajax views
Home-page: https://github.com/peopledoc/django-chartjs
Author: Rémy Hubscher
Author-email: hubscher.remy@gmail.com
License: BSD Licence
Keywords: django chart chartjs highchart ajax class based views
Platform: UNKNOWN
Classifier: Development Status :: 4 - Beta
Classifier: Environment :: Web Environment
Classifier: Framework :: Django
Classifier: Framework :: Django :: 1.10
Classifier: Framework :: Django :: 2.2
Classifier: Framework :: Django :: 3.0
Classifier: Intended Audience :: Developers
Classifier: License :: OSI Approved :: BSD License
Classifier: Programming Language :: Python
Classifier: Programming Language :: Python :: 3
Classifier: Programming Language :: Python :: 3.6
Classifier: Programming Language :: Python :: 3.7
Classifier: Programming Language :: Python :: 3.8
